[{
	"kind": "wmw",
	"features": ["вмв54.geojson"],
	"name": "Операция «Пьедестал»",
	"startDate": "03.08.1942",
	"endDate": "15.08.1942",
	"allies": "Великобритания",
	"enemies": "Германия, Италия",
	"ally_airplans_cnt": "102.0",
	"ally_ships_cnt": "59.0",
	"ally_deads": "550.0",
	"ally_airplans_lost": "34.0",
	"ally_ships_lost": "13.0",
	"enem_airplans_cnt": "589.0",
	"enem_ships_cnt": "21.0",
	"enem_submarines_cnt": "11.0",
	"enem_deads": "ок.100",
	"enem_airplans_lost": "60.0",
	"enem_submarines_lost": "2.0",
	"winner": "Германия",
	"comment": "У Великобритании повреждены 1 авианосец, 2 лёгких крейсера, 3 вспомогательных судна; у Германии повреждены 1 тяжёлый крейсер, 1 лёгкий крейсер, 1 субмарина ",
	"source_url": "https://ru.wikipedia.org/wiki/Операция_«Пьедестал»",
	"imgUrl": "https://upload.wikimedia.org/wikipedia/ru/5/59/Operation_Pedestal_ru.JPG"
}]