[{
	"kind": "wmw",
	"features": ["вмв62.geojson"],
	"name": "Бой у островов Санта-Крус",
	"startDate": "25.10.1942",
	"endDate": "27.10.1942",
	"allies": "США",
	"enemies": "Япония",
	"ally_airplans_cnt": "177.0",
	"ally_ships_cnt": "23.0",
	"ally_deads": "266.0",
	"ally_airplans_lost": "81.0",
	"ally_ships_lost": "2.0",
	"enem_airplans_cnt": "203.0",
	"enem_ships_cnt": "43.0",
	"enem_deads": "500.0",
	"enem_airplans_lost": "99.0",
	"winner": "Япония",
	"comment": "У США повреждены 1 авианосец и 2 эсминца; у Японии повреждены 2 авианосца и 1 тяжёлый крейсер ",
	"source_url": "https://ru.wikipedia.org/wiki/Бой_у_островов_Санта-Крус",
	"imgUrl": "http://ibiblio.org/hyperwar/USN/USN-CN-SantaCruz/maps/USN-CN-SantaCruz-1.jpg"
}]